{
  "mood_great": {
    "precision": 0.0,
    "recall": 0.0,
    "f1-score": 0.0,
    "support": 2
  },
  "bot_challenge": {
    "precision": 0.0,
    "recall": 0.0,
    "f1-score": 0.0,
    "support": 1
  },
  "utter_greet": {
    "precision": 1.0,
    "recall": 1.0,
    "f1-score": 1.0,
    "support": 5
  },
  "deny": {
    "precision": 0.0,
    "recall": 0.0,
    "f1-score": 0.0,
    "support": 2
  },
  "utter_iamabot": {
    "precision": 0.0,
    "recall": 0.0,
    "f1-score": 0.0,
    "support": 1
  },
  "utter_goodbye": {
    "precision": 0.0,
    "recall": 0.0,
    "f1-score": 0.0,
    "support": 4
  },
  "utter_cheer_up": {
    "precision": 0.0,
    "recall": 0.0,
    "f1-score": 0.0,
    "support": 3
  },
  "mood_unhappy": {
    "precision": 0.0,
    "recall": 0.0,
    "f1-score": 0.0,
    "support": 3
  },
  "greet": {
    "precision": 0.7142857142857143,
    "recall": 1.0,
    "f1-score": 0.8333333333333333,
    "support": 5
  },
  "action_listen": {
    "precision": 0.8421052631578947,
    "recall": 1.0,
    "f1-score": 0.9142857142857143,
    "support": 16
  },
  "goodbye": {
    "precision": 0.0,
    "recall": 0.0,
    "f1-score": 0.0,
    "support": 2
  },
  "utter_happy": {
    "precision": 0.0,
    "recall": 0.0,
    "f1-score": 0.0,
    "support": 3
  },
  "affirm": {
    "precision": 0.0,
    "recall": 0.0,
    "f1-score": 0.0,
    "support": 1
  },
  "utter_did_that_help": {
    "precision": 0.0,
    "recall": 0.0,
    "f1-score": 0.0,
    "support": 3
  },
  "micro avg": {
    "precision": 0.8387096774193549,
    "recall": 0.5098039215686274,
    "f1-score": 0.6341463414634145,
    "support": 51
  },
  "macro avg": {
    "precision": 0.18259935553168635,
    "recall": 0.21428571428571427,
    "f1-score": 0.19625850340136056,
    "support": 51
  },
  "weighted avg": {
    "precision": 0.4322571133716644,
    "recall": 0.5098039215686274,
    "f1-score": 0.46657329598506064,
    "support": 51
  },
  "accuracy": 0.5098039215686274,
  "conversation_accuracy": {
    "accuracy": 0.0,
    "correct": 0,
    "with_warnings": 0,
    "total": 7
  }
}