{"py/object": "rasa.core.featurizers.tracker_featurizers.MaxHistoryTrackerFeaturizer", "state_featurizer": {"py/object": "rasa.core.featurizers.single_state_featurizer.SingleStateFeaturizer", "_default_feature_states": {"intent": {"B2": 0, "B2_ar": 1, "B2_fr": 2, "absence_examen_ang": 3, "absence_examen_fr": 4, "administration_fr": 5, "admis_ang": 6, "admis_fr": 7, "admission_ang": 8, "admission_ar": 9, "admission_fr": 10, "alternance_ang": 11, "alternance_ar": 12, "alternance_fr": 13, "annulation_inscription_eng": 14, "annulation_inscription_fr": 15, "applicabilite_formation_fr": 16, "avantage_alternance": 17, "avantage_alternance_ar": 18, "avantage_alternance_eng": 19, "avantage_esprit_fr": 20, "back": 21, "bye": 22, "bye_ar": 23, "byefr": 24, "carte_amen_ang": 25, "carte_amen_fr": 26, "certificat": 27, "certificat_ar": 28, "classe_1ere_fr": 29, "classe_ang": 30, "club_eng": 31, "club_fr": 32, "concours_admission_ar": 33, "concours_admission_eng": 34, "concours_admission_fr": 35, "confirmation_option_eng": 36, "confirmation_option_fr": 37, "conseil_classe_eng": 38, "conseil_classe_fr": 39, "contact": 40, "contact_ar": 41, "courssoir": 42, "courssoir_ar": 43, "courssoir_eng": 44, "cout_formation_ar": 45, "cout_formation_eng": 46, "cout_formation_fr": 47, "cout_hebergement_ang": 48, "cout_hebergement_fr": 49, "cout_restauration_ang": 50, "cout_restauration_fr": 51, "covidSession": 52, "covidSession_fr": 53, "credit_eng": 54, "credit_fr": 55, "date_preinscription_ar": 56, "date_preinscription_eng": 57, "date_preinscription_fr": 58, "date_res_ang": 59, "date_res_fr": 60, "difference_3A_3B_ar": 61, "difference_3A_3B_eng": 62, "difference_3A_3B_fr": 63, "double_correction_eng": 64, "double_correction_fr": 65, "double_diplome": 66, "double_diplome_ar": 67, "exemples_rapport_stage_eng": 68, "exemples_rapport_stage_fr": 69, "filiere_ang": 70, "filiere_fr": 71, "greet": 72, "info_generale_esprit": 73, "info_generale_esprit_ar": 74, "inscri_bac_ang": 75, "inscri_bac_ar": 76, "inscri_bac_fr": 77, "inscri_ing_info_ang": 78, "inscri_ing_info_ar": 79, "inscri_ing_info_fr": 80, "licence_info_ang": 81, "licence_info_ar": 82, "licence_info_fr": 83, "lien_doc_ang": 84, "lien_video_ang": 85, "mobilite_internationale": 86, "mobilite_internationale_ar": 87, "mobilite_internationale_eng": 88, "modalite_ang": 89, "modalite_ar": 90, "modalite_fr": 91, "modalites_paiement_ar": 92, "modalites_paiement_eng": 93, "modalites_paiement_fr": 94, "nlu_fallback": 95, "note_ar": 96, "note_eng": 97, "note_fr": 98, "obtention_diplome_ang": 99, "obtention_diplome_fr": 100, "out_of_scope": 101, "paiement_par_tranche_fr": 102, "partenaires_fr": 103, "pcr_ang": 104, "pcr_fr": 105, "photo_foyer_eng": 106, "photo_foyer_externe_eng": 107, "photo_foyer_externe_fr": 108, "photo_foyer_fr": 109, "photo_foyer_interne_eng": 110, "photo_foyer_interne_fr": 111, "place_ang": 112, "place_ar": 113, "place_fr": 114, "procedure_inscription_fr": 115, "procedure_stage_eng": 116, "procedure_stage_fr": 117, "ratt_ang": 118, "ratt_fr": 119, "reclamation_confirmation_admission_ar": 120, "reclamation_confirmation_admission_eng": 121, "reclamation_confirmation_admission_fr": 122, "reconnaissance_diplome_fr": 123, "redoublement_ang": 124, "redoublement_fr": 125, "reduction_premier_fr": 126, "regime_etude_eng": 127, "regime_etude_fr": 128, "remerciement": 129, "remerciement_ar": 130, "rentree_ang": 131, "rentree_ar": 132, "rentree_fr": 133, "reporter_entretien_ar": 134, "reporter_entretien_eng": 135, "reporter_entretien_fr": 136, "restart": 137, "salutation": 138, "salutation_ar": 139, "session_start": 140, "stage": 141, "stage_ar": 142, "thanks": 143, "valider_module_ang": 144, "valider_module_fr": 145}, "action_name": {"action_listen": 0, "action_restart": 1, "action_session_start": 2, "action_default_fallback": 3, "action_deactivate_loop": 4, "action_revert_fallback_events": 5, "action_default_ask_affirmation": 6, "action_default_ask_rephrase": 7, "action_two_stage_fallback": 8, "action_unlikely_intent": 9, "action_back": 10, "...": 11, "action_extract_slots": 12, "action_ask_nationality": 13, "action_get_price_tunisian": 14, "action_get_price_foreigner": 15, "utter_B2": 16, "utter_B2_fr": 17, "utter_absence_examen_ang": 18, "utter_absence_examen_fr": 19, "utter_admis_ang": 20, "utter_admis_fr": 21, "utter_admission_ang": 22, "utter_admission_fr": 23, "utter_alternance_ang": 24, "utter_alternance_fr": 25, "utter_annulation_inscription_eng": 26, "utter_annulation_inscription_fr": 27, "utter_ask_nationality": 28, "utter_avantage_alternance": 29, "utter_avantage_alternance_eng": 30, "utter_bye": 31, "utter_byefr": 32, "utter_carte_amen_ang": 33, "utter_carte_amen_fr": 34, "utter_classe_ang": 35, "utter_classe_fr": 36, "utter_club_eng": 37, "utter_club_fr": 38, "utter_concours_admission_eng": 39, "utter_concours_admission_fr": 40, "utter_confirmation_option_eng": 41, "utter_confirmation_option_fr": 42, "utter_conseil_classe_eng": 43, "utter_conseil_classe_fr": 44, "utter_contact": 45, "utter_courssoir": 46, "utter_courssoir_eng": 47, "utter_cout_formation_eng": 48, "utter_cout_formation_fr": 49, "utter_cout_hebergement_ang": 50, "utter_cout_hebergement_fr": 51, "utter_cout_restauration_ang": 52, "utter_cout_restauration_fr": 53, "utter_covidSession": 54, "utter_covidSession_fr": 55, "utter_credit_eng": 56, "utter_credit_fr": 57, "utter_date_preinscription_eng": 58, "utter_date_preinscription_fr": 59, "utter_date_res_ang": 60, "utter_date_res_fr": 61, "utter_default": 62, "utter_details_thanks": 63, "utter_difference_3A_3B_eng": 64, "utter_difference_3A_3B_fr": 65, "utter_double_correction_eng": 66, "utter_double_correction_fr": 67, "utter_exemples_rapport_stage_eng": 68, "utter_exemples_rapport_stage_fr": 69, "utter_first_message": 70, "utter_greet": 71, "utter_iamabot": 72, "utter_inscri_bac_ang": 73, "utter_inscri_bac_fr": 74, "utter_inscri_ing_info_ang": 75, "utter_inscri_ing_info_fr": 76, "utter_licence_info_ang": 77, "utter_licence_info_fr": 78, "utter_lien_doc": 79, "utter_lien_video": 80, "utter_mobilite_internationale": 81, "utter_mobilite_internationale_eng": 82, "utter_modalite_ang": 83, "utter_modalite_fr": 84, "utter_modalites_paiement_eng": 85, "utter_modalites_paiement_fr": 86, "utter_note_eng": 87, "utter_note_fr": 88, "utter_obtention_diplome_ang": 89, "utter_obtention_diplome_fr": 90, "utter_pcr_ang": 91, "utter_pcr_fr": 92, "utter_photo_foyer1": 93, "utter_photo_foyer2": 94, "utter_photo_foyer3": 95, "utter_photo_foyer_externe1": 96, "utter_photo_foyer_externe2": 97, "utter_photo_foyer_externe3": 98, "utter_place_ang": 99, "utter_place_fr": 100, "utter_price_foreigner": 101, "utter_price_tunisian": 102, "utter_procedure_stage_eng": 103, "utter_procedure_stage_fr": 104, "utter_ratt_ang": 105, "utter_ratt_fr": 106, "utter_reclamation_confirmation_admission_eng": 107, "utter_reclamation_confirmation_admission_fr": 108, "utter_redoublement_ang": 109, "utter_redoublement_fr": 110, "utter_regime_etude_eng": 111, "utter_regime_etude_fr": 112, "utter_remerciement": 113, "utter_rentree_ang": 114, "utter_rentree_fr": 115, "utter_reporter_entretien_eng": 116, "utter_reporter_entretien_fr": 117, "utter_salutation": 118, "utter_thanks": 119, "utter_type_foyer_eng": 120, "utter_type_foyer_fr": 121, "utter_type_visualisation_ang": 122, "utter_type_visualisation_fr": 123, "utter_valider_module_ang": 124, "utter_valider_module_fr": 125}, "entities": {"nationality": 0}, "slots": {}, "active_loop": {}}, "action_texts": [], "entity_tag_specs": null}, "max_history": 5, "remove_duplicates": true}